graph_vect_rag/__init__.py
graph_vect_rag/exceptions.py
graph_vect_rag/graph_rag_engine.py
graph_vect_rag/retreiver.py
graph_vect_rag-1.0.1.dist-info/LICENSE.txt
graph_vect_rag-1.0.1.dist-info/METADATA
graph_vect_rag-1.0.1.dist-info/WHEEL
graph_vect_rag-1.0.1.dist-info/top_level.txt
graph_vect_rag-1.0.1.dist-info/RECORD
